calblock.py
calblock-0.1.1.dist-info/licenses/LICENSE
calblock-0.1.1.dist-info/METADATA
calblock-0.1.1.dist-info/WHEEL
calblock-0.1.1.dist-info/entry_points.txt
calblock-0.1.1.dist-info/top_level.txt
calblock-0.1.1.dist-info/RECORD
