Metadata-Version: 2.4
Name: calblock
Version: 0.1.1
Summary: Automatically block free time in Microsoft 365 calendar when below threshold
Author-email: Sebastian Funk <sebastian.funk@lshtm.ac.uk>
License: MIT
Project-URL: Homepage, https://github.com/sbfnk/calblock
Project-URL: Repository, https://github.com/sbfnk/calblock
Project-URL: Issues, https://github.com/sbfnk/calblock/issues
Requires-Python: >=3.6
License-File: LICENSE
Requires-Dist: requests
Requires-Dist: pyyaml
Requires-Dist: python-dateutil
Requires-Dist: m365auth
Requires-Dist: tzdata
Dynamic: license-file
